sony_camera_server/__init__.py
sony_camera_server/device_cache.py
sony_camera_server/sony_http_server.py
sony_camera_server/sony_imgdev.py
sony_camera_server/sony_media_erase.py
sony_camera_server/sony_media_transfer.py
sony_camera_server/sony_snap_picture.py
sony_camera_server/sony_streams.py
sony_camera_server/ssdp.py
sony_camera_server/xml2dict.py
sony_camera_server/res/__init__.py
sony_camera_server/res/favicon.svg
sony_camera_server/res/index.html
sony_camera_server/res/script.js
sony_camera_server/res/styling.css
sony_camera_server-0.0.5.dist-info/LICENSE
sony_camera_server-0.0.5.dist-info/METADATA
sony_camera_server-0.0.5.dist-info/WHEEL
sony_camera_server-0.0.5.dist-info/entry_points.txt
sony_camera_server-0.0.5.dist-info/top_level.txt
sony_camera_server-0.0.5.dist-info/RECORD
