Metadata-Version: 2.1
Name: sony-camera-server
Version: 0.0.5
Summary: A package for controlling Sony Imaging Devices
Home-page: https://github.com/Xaldew/sony-camera-server
Author: Gustaf Waldemarson
Author-email: gustaf.waldemarson@gmail.com
License: UNKNOWN
Project-URL: Bug Tracker, https://github.com/Xaldew/sony-camera-server/issues
Platform: UNKNOWN
Classifier: Programming Language :: Python :: 3
Classifier: License :: OSI Approved :: GNU General Public License v3 or later (GPLv3+)
Classifier: Operating System :: OS Independent
Requires-Python: >=3.6
License-File: LICENSE
